nutritranslate/__init__.py
nutritranslate/nt.py
nutritranslate-0.5.7.dist-info/DESCRIPTION.rst
nutritranslate-0.5.7.dist-info/METADATA
nutritranslate-0.5.7.dist-info/RECORD
nutritranslate-0.5.7.dist-info/WHEEL
nutritranslate-0.5.7.dist-info/metadata.json
nutritranslate-0.5.7.dist-info/top_level.txt
