Metadata-Version: 2.0
Name: nutritranslate
Version: 0.5.7
Summary: A service that translates and normalizes food nutrients
Home-page: https://github.com/ineeve/nutrients-translator
Author: Renato Campos
Author-email: renatoineeve@gmail.com
License: MIT
Platform: UNKNOWN
Requires-Python: >=3.6
